augmentex/__init__.py
augmentex/base.py
augmentex/char.py
augmentex/preprocessor.py
augmentex/punc.py
augmentex/variables.py
augmentex/word.py
augmentex/static_data/mobile_typos_chars.json
augmentex/static_data/pc_typos_chars.json
augmentex/static_data/shift.json
augmentex/static_data/eng/stopwords.json
augmentex/static_data/eng/text2emoji.json
augmentex/static_data/eng/vocab.json
augmentex/static_data/eng/mobile/orfo_chars.json
augmentex/static_data/eng/mobile/orfo_ngrams.json
augmentex/static_data/eng/mobile/orfo_words.json
augmentex/static_data/eng/pc/orfo_chars.json
augmentex/static_data/eng/pc/orfo_ngrams.json
augmentex/static_data/eng/pc/orfo_words.json
augmentex/static_data/rus/stopwords.json
augmentex/static_data/rus/text2emoji.json
augmentex/static_data/rus/vocab.json
augmentex/static_data/rus/mobile/orfo_chars.json
augmentex/static_data/rus/mobile/orfo_ngrams.json
augmentex/static_data/rus/mobile/orfo_words.json
augmentex/static_data/rus/pc/orfo_chars.json
augmentex/static_data/rus/pc/orfo_ngrams.json
augmentex/static_data/rus/pc/orfo_words.json
augmentex-1.3.1.data/data/static_data/mobile_typos_chars.json
augmentex-1.3.1.data/data/static_data/orfo_chars.json
augmentex-1.3.1.data/data/static_data/orfo_ngrams.json
augmentex-1.3.1.data/data/static_data/orfo_words.json
augmentex-1.3.1.data/data/static_data/pc_typos_chars.json
augmentex-1.3.1.data/data/static_data/shift.json
augmentex-1.3.1.data/data/static_data/stopwords.json
augmentex-1.3.1.data/data/static_data/text2emoji.json
augmentex-1.3.1.data/data/static_data/vocab.json
augmentex-1.3.1.dist-info/LICENSE
augmentex-1.3.1.dist-info/METADATA
augmentex-1.3.1.dist-info/WHEEL
augmentex-1.3.1.dist-info/top_level.txt
augmentex-1.3.1.dist-info/RECORD
