Metadata-Version: 2.1
Name: augmentex
Version: 1.3.1
Summary: Augmentex — a library for augmenting texts with errors
Home-page: https://github.com/ai-forever/augmentex
Author: Mark Baushenko and Alexandr Abramov
Author-email: m.baushenko@gmail.com
License: MIT
Keywords: augmentex errors typos nlp augmentation
Classifier: Natural Language :: English
Classifier: Natural Language :: Russian
Classifier: Programming Language :: Python :: 3.7
Classifier: Programming Language :: Python :: 3.8
Classifier: Programming Language :: Python :: 3.9
Classifier: Programming Language :: Python :: 3.10
Classifier: Topic :: Scientific/Engineering :: Artificial Intelligence
Classifier: Topic :: Software Development :: Libraries :: Python Modules
Classifier: Topic :: Text Editors :: Text Processing
Requires-Python: >=3.7.0
License-File: LICENSE
Requires-Dist: numpy>=1.21
Requires-Dist: python-Levenshtein>=0.22.0
